gocd_cli/__init__.py
gocd_cli/commands/__init__.py
gocd_cli/commands/echo.py
gocd_cli.commands.echo-1.0.dist-info/DESCRIPTION.rst
gocd_cli.commands.echo-1.0.dist-info/METADATA
gocd_cli.commands.echo-1.0.dist-info/metadata.json
gocd_cli.commands.echo-1.0.dist-info/pbr.json
gocd_cli.commands.echo-1.0.dist-info/RECORD
gocd_cli.commands.echo-1.0.dist-info/top_level.txt
gocd_cli.commands.echo-1.0.dist-info/WHEEL
