Metadata-Version: 2.0
Name: gocd-cli.commands.echo
Version: 1.0
Summary: An example echo command
Home-page: UNKNOWN
Author: Björn Andersson
Author-email: ba@sanitarium.se
License: MIT License
Platform: UNKNOWN
Requires-Dist: gocd-cli (>=0.7,<1.0)
